[
  {
    "_id": "658b5ea6b64d0454f3978319",
    "zoom_id": "9U4fVlbMRsKuQgOf1kpYBg",
    "first_name": "Steve",
    "last_name": "Calla",
    "display_name": "Steve Calla",
    "email": "callasteven@gmail.com",
    "role_name": "Owner",
    "timezone": "America/Denver",
    "last_client_version": "5.16.10.25689(mac)",
    "pic_url": "https://us04web.zoom.us/p/9U4fVlbMRsKuQgOf1kpYBg/f15b3e8c-9374-4f1e-9185-0b39a2e2c234-7189",
    "language": "en-US",
    "zoom_status": "active",
    "job_title": "",
    "location": "Boulder, CO",
    "login_types": [1, 100],
    "phone_numbers": [
      {
        "country": "US",
        "code": "+1",
        "number": "2019347068",
        "verified": true,
        "label": ""
      }
    ],
    "user_created_at": "2020-10-02T14:26:57Z",
    "is_installed": true,
    "user": "6498fb54494aa98f85992da5"
  }
]